.gitignore
CHANGELOG.rst
LICENSE.rst
README.rst
pyproject.toml
readthedocs.yml
setup.cfg
.github/workflows/ccsdspy-ci.yml
.github/workflows/doc-build.yml
ccsdspy/__init__.py
ccsdspy/__main__.py
ccsdspy/_version.py
ccsdspy/constants.py
ccsdspy/converters.py
ccsdspy/decode.py
ccsdspy/packet_fields.py
ccsdspy/packet_types.py
ccsdspy/utils.py
ccsdspy.egg-info/PKG-INFO
ccsdspy.egg-info/SOURCES.txt
ccsdspy.egg-info/dependency_links.txt
ccsdspy.egg-info/requires.txt
ccsdspy.egg-info/top_level.txt
ccsdspy/tests/__init__.py
ccsdspy/tests/test_byte_order.py
ccsdspy/tests/test_converters.py
ccsdspy/tests/test_hs.py
ccsdspy/tests/test_packet_fields.py
ccsdspy/tests/test_packet_types.py
ccsdspy/tests/test_primary_header.py
ccsdspy/tests/test_regression.py
ccsdspy/tests/test_split.py
ccsdspy/tests/test_utils.py
ccsdspy/tests/test_var_length.py
ccsdspy/tests/data/byte_order/byte_order_packets.py
ccsdspy/tests/data/byte_order/byteorder_1.bin
ccsdspy/tests/data/byte_order/byteorder_1.csv
ccsdspy/tests/data/byte_order/byteorder_12.bin
ccsdspy/tests/data/byte_order/byteorder_12.csv
ccsdspy/tests/data/byte_order/byteorder_123.bin
ccsdspy/tests/data/byte_order/byteorder_123.csv
ccsdspy/tests/data/byte_order/byteorder_1234.bin
ccsdspy/tests/data/byte_order/byteorder_1234.csv
ccsdspy/tests/data/byte_order/byteorder_123456.bin
ccsdspy/tests/data/byte_order/byteorder_123456.csv
ccsdspy/tests/data/byte_order/byteorder_1234567.bin
ccsdspy/tests/data/byte_order/byteorder_1234567.csv
ccsdspy/tests/data/byte_order/byteorder_12345678.bin
ccsdspy/tests/data/byte_order/byteorder_12345678.csv
ccsdspy/tests/data/byte_order/byteorder_21.bin
ccsdspy/tests/data/byte_order/byteorder_21.csv
ccsdspy/tests/data/byte_order/byteorder_2143.bin
ccsdspy/tests/data/byte_order/byteorder_2143.csv
ccsdspy/tests/data/byte_order/byteorder_321.bin
ccsdspy/tests/data/byte_order/byteorder_321.csv
ccsdspy/tests/data/byte_order/byteorder_3412.bin
ccsdspy/tests/data/byte_order/byteorder_3412.csv
ccsdspy/tests/data/byte_order/byteorder_4321.bin
ccsdspy/tests/data/byte_order/byteorder_4321.csv
ccsdspy/tests/data/byte_order/byteorder_78563412.bin
