Metadata-Version: 2.4
Name: ccsdspy
Version: 1.4.3
Summary: IO Interface for Reading CCSDS Data in Python.
Author-email: Daniel da Silva <mail@danieldasilva.org>, Steven Christe <steven.d.christe@nasa.gov>
License: Copyright (c) 2018, Daniel da Silva
Keywords: python,nasa,ccsds,space packet protocol
Classifier: Development Status :: 5 - Production/Stable
Classifier: Intended Audience :: Science/Research
Classifier: Programming Language :: Python :: 3.6
Classifier: Programming Language :: Python :: 3.7
Classifier: Programming Language :: Python :: 3.8
Classifier: Programming Language :: Python :: 3.9
Classifier: Programming Language :: Python :: 3.10
Classifier: Programming Language :: Python :: 3.11
Classifier: Programming Language :: Python :: 3.12
Classifier: Programming Language :: Python :: 3.13
Classifier: License :: OSI Approved :: BSD License
Classifier: Operating System :: OS Independent
Requires-Python: >=3.6
License-File: LICENSE.rst
Requires-Dist: numpy>=1.8.0
Provides-Extra: dev
Requires-Dist: coverage>=6.5.0; extra == "dev"
Requires-Dist: pytest<8.1.0,>=7.1.3; extra == "dev"
Requires-Dist: pytest-astropy; extra == "dev"
Requires-Dist: pytest-cov; extra == "dev"
Requires-Dist: black==22.10.0; extra == "dev"
Requires-Dist: flake8>=5.0.4; extra == "dev"
Requires-Dist: coverage[toml]; extra == "dev"
Provides-Extra: docs
Requires-Dist: sphinx>=5.2.3; extra == "docs"
Requires-Dist: sphinx-automodapi>=0.14.1; extra == "docs"
Requires-Dist: graphviz>=0.20.1; extra == "docs"
Requires-Dist: numpydoc; extra == "docs"
Dynamic: license-file
